sequent.cpython-311-darwin.so
sequent/__init__.py
sequent/sequent.c
quent-1.0.0.dist-info/LICENSE
quent-1.0.0.dist-info/METADATA
quent-1.0.0.dist-info/WHEEL
quent-1.0.0.dist-info/top_level.txt
quent-1.0.0.dist-info/RECORD
