Metadata-Version: 2.1
Name: quent
Version: 1.0.0
Summary: Sequent helps you write clearer code.
Author-email: Ohad Drukman <drukmano@icloud.com>
License: MIT License
Project-URL: repository, https://github.com/drukmano/sequent.git
Classifier: License :: OSI Approved :: MIT License
Classifier: Intended Audience :: Developers
Classifier: Programming Language :: Python
Classifier: Programming Language :: Cython
Classifier: Operating System :: OS Independent
Classifier: Topic :: Software Development
Classifier: Topic :: Software Development :: Libraries :: Python Modules
Requires-Python: >=3.7
License-File: LICENSE
